[{"stno": "C0G650", "date": "19960901", "TX01": 29.1, "PP01": 0.0, "RH01": -9999, "WD01": 0.2, "SS01": 3.8}, {"stno": "C0G650", "date": "19960902", "TX01": 28.3, "PP01": 0.0, "RH01": -9999, "WD01": 0.2, "SS01": 1.2}, {"stno": "C0G650", "date": "19960903", "TX01": 26.7, "PP01": 2.5, "RH01": -9999, "WD01": 0.4, "SS01": 2.2}, {"stno": "C0G650", "date": "19960904", "TX01": 27.7, "PP01": 0.0, "RH01": -9999, "WD01": 0.5, "SS01": 7.7}, {"stno": "C0G650", "date": "19960905", "TX01": 27.4, "PP01": 0.0, "RH01": -9999, "WD01": 0.4, "SS01": 4.0}, {"stno": "C0G650", "date": "19960906", "TX01": 27.0, "PP01": 0.5, "RH01": -9999, "WD01": 0.6, "SS01": 3.8}, {"stno": "C0G650", "date": "19960907", "TX01": 28.1, "PP01": 0.0, "RH01": -9999, "WD01": 0.3, "SS01": 7.7}, {"stno": "C0G650", "date": "19960908", "TX01": 28.9, "PP01": 0.0, "RH01": -9999, "WD01": 0.3, "SS01": 2.1}, {"stno": "C0G650", "date": "19960909", "TX01": 30.0, "PP01": 0.0, "RH01": -9999, "WD01": 0.3, "SS01": 7.6}, {"stno": "C0G650", "date": "19960910", "TX01": 29.0, "PP01": 0.0, "RH01": -9999, "WD01": 0.3, "SS01": 0.6}, {"stno": "C0G650", "date": "19960911", "TX01": 29.1, "PP01": 0.0, "RH01": -9999, "WD01": 0.4, "SS01": 2.3}, {"stno": "C0G650", "date": "19960912", "TX01": 28.9, "PP01": 0.0, "RH01": -9999, "WD01": 0.2, "SS01": 1.2}, {"stno": "C0G650", "date": "19960913", "TX01": 28.7, "PP01": 0.0, "RH01": -9999, "WD01": 0.2, "SS01": 3.1}, {"stno": "C0G650", "date": "19960914", "TX01": 28.4, "PP01": 0.0, "RH01": -9999, "WD01": 0.2, "SS01": 3.3}, {"stno": "C0G650", "date": "19960915", "TX01": 28.3, "PP01": 0.0, "RH01": -9999, "WD01": 0.1, "SS01": 0.4}, {"stno": "C0G650", "date": "19960916", "TX01": 28.5, "PP01": 0.0, "RH01": -9999, "WD01": 0.2, "SS01": 0.4}, {"stno": "C0G650", "date": "19960917", "TX01": 28.7, "PP01": 0.0, "RH01": -9999, "WD01": 0.4, "SS01": 5.6}, {"stno": "C0G650", "date": "19960918", "TX01": 28.8, "PP01": 0.0, "RH01": -9999, "WD01": 0.4, "SS01": 6.4}, {"stno": "C0G650", "date": "19960919", "TX01": 28.3, "PP01": 0.0, "RH01": -9999, "WD01": 0.1, "SS01": 6.0}, {"stno": "C0G650", "date": "19960920", "TX01": 28.5, "PP01": 0.0, "RH01": -9999, "WD01": 0.3, "SS01": 5.5}, {"stno": "C0G650", "date": "19960921", "TX01": 28.4, "PP01": 0.0, "RH01": -9999, "WD01": 0.4, "SS01": 6.4}, {"stno": "C0G650", "date": "19960922", "TX01": 28.1, "PP01": 0.0, "RH01": -9999, "WD01": 0.2, "SS01": 2.6}, {"stno": "C0G650", "date": "19960923", "TX01": 27.7, "PP01": 0.0, "RH01": -9999, "WD01": 0.4, "SS01": 2.7}, {"stno": "C0G650", "date": "19960924", "TX01": 26.6, "PP01": 3.0, "RH01": -9999, "WD01": 0.6, "SS01": 1.5}, {"stno": "C0G650", "date": "19960925", "TX01": 27.2, "PP01": 0.0, "RH01": -9999, "WD01": 0.6, "SS01": 2.1}, {"stno": "C0G650", "date": "19960926", "TX01": 27.6, "PP01": 0.0, "RH01": -9999, "WD01": 0.5, "SS01": 6.5}, {"stno": "C0G650", "date": "19960927", "TX01": 27.5, "PP01": 0.0, "RH01": -9999, "WD01": 1.6, "SS01": 7.2}, {"stno": "C0G650", "date": "19960928", "TX01": 25.8, "PP01": 1.0, "RH01": -9999, "WD01": 2.5, "SS01": 0.2}, {"stno": "C0G650", "date": "19960929", "TX01": 25.4, "PP01": 0.0, "RH01": -9999, "WD01": 3.3, "SS01": 4.5}, {"stno": "C0G650", "date": "19960930", "TX01": 25.3, "PP01": 0.0, "RH01": -9999, "WD01": 1.7, "SS01": 7.3}, {"stno": "C0G660", "date": "19960901", "TX01": -9999, "PP01": 0.0, "RH01": -9999, "WD01": -9999, "SS01": -9999}, {"stno": "C0G660", "date": "19960902", "TX01": -9999, "PP01": 1.0, "RH01": -9999, "WD01": -9999, "SS01": -9999}, {"stno": "C0G660", "date": "19960903", "TX01": -9999, "PP01": 0.0, "RH01": -9999, "WD01": -9999, "SS01": -9999}, {"stno": "C0G660", "date": "19960904", "TX01": -9999, "PP01": 0.0, "RH01": -9999, "WD01": -9999, "SS01": -9999}, {"stno": "C0G660", "date": "19960905", "TX01": -9999, "PP01": 0.0, "RH01": -9999, "WD01": -9999, "SS01": -9999}, {"stno": "C0G660", "date": "19960906", "TX01": -9999, "PP01": 0.0, "RH01": -9999, "WD01": -9999, "SS01": -9999}, {"stno": "C0G660", "date": "19960907", "TX01": -9999, "PP01": 0.0, "RH01": -9999, "WD01": -9999, "SS01": -9999}, {"stno": "C0G660", "date": "19960908", "TX01": -9999, "PP01": 0.0, "RH01": -9999, "WD01": -9999, "SS01": -9999}, {"stno": "C0G660", "date": "19960909", "TX01": -9999, "PP01": 0.0, "RH01": -9999, "WD01": -9999, "SS01": -9999}, {"stno": "C0G660", "date": "19960910", "TX01": -9999, "PP01": 0.0, "RH01": -9999, "WD01": -9999, "SS01": -9999}, {"stno": "C0G660", "date": "19960911", "TX01": -9999, "PP01": 0.0, "RH01": -9999, "WD01": -9999, "SS01": -9999}, {"stno": "C0G660", "date": "19960912", "TX01": -9999, "PP01": 0.0, "RH01": -9999, "WD01": -9999, "SS01": -9999}, {"stno": "C0G660", "date": "19960913", "TX01": -9999, "PP01": 0.0, "RH01": -9999, "WD01": -9999, "SS01": -9999}, {"stno": "C0G660", "date": "19960914", "TX01": -9999, "PP01": 0.0, "RH01": -9999, "WD01": -9999, "SS01": -9999}, {"stno": "C0G660", "date": "19960915", "TX01": -9999, "PP01": 0.0, "RH01": -9999, "WD01": -9999, "SS01": -9999}, {"stno": "C0G660", "date": "19960916", "TX01": -9999, "PP01": 0.0, "RH01": -9999, "WD01": -9999, "SS01": -9999}, {"stno": "C0G660", "date": "19960917", "TX01": -9999, "PP01": 0.0, "RH01": -9999, "WD01": -9999, "SS01": -9999}, {"stno": "C0G660", "date": "19960918", "TX01": -9999, "PP01": 0.0, "RH01": -9999, "WD01": -9999, "SS01": -9999}, {"stno": "C0G660", "date": "19960919", "TX01": -9999, "PP01": 0.0, "RH01": -9999, "WD01": -9999, "SS01": -9999}, {"stno": "C0G660", "date": "19960920", "TX01": -9999, "PP01": 0.0, "RH01": -9999, "WD01": -9999, "SS01": -9999}, {"stno": "C0G660", "date": "19960921", "TX01": -9999, "PP01": 0.0, "RH01": -9999, "WD01": -9999, "SS01": -9999}, {"stno": "C0G660", "date": "19960922", "TX01": -9999, "PP01": 0.0, "RH01": -9999, "WD01": -9999, "SS01": -9999}, {"stno": "C0G660", "date": "19960923", "TX01": -9999, "PP01": 0.0, "RH01": -9999, "WD01": -9999, "SS01": -9999}, {"stno": "C0G660", "date": "19960924", "TX01": -9999, "PP01": 0.0, "RH01": -9999, "WD01": -9999, "SS01": -9999}, {"stno": "C0G660", "date": "19960925", "TX01": -9999, "PP01": 0.0, "RH01": -9999, "WD01": -9999, "SS01": -9999}, {"stno": "C0G660", "date": "19960926", "TX01": -9999, "PP01": 0.0, "RH01": -9999, "WD01": -9999, "SS01": -9999}, {"stno": "C0G660", "date": "19960927", "TX01": -9999, "PP01": 0.0, "RH01": -9999, "WD01": -9999, "SS01": -9999}, {"stno": "C0G660", "date": "19960928", "TX01": -9999, "PP01": 0.0, "RH01": -9999, "WD01": -9999, "SS01": -9999}, {"stno": "C0G660", "date": "19960929", "TX01": -9999, "PP01": 0.0, "RH01": -9999, "WD01": -9999, "SS01": -9999}, {"stno": "C0G660", "date": "19960930", "TX01": -9999, "PP01": 0.0, "RH01": -9999, "WD01": -9999, "SS01": -9999}]